distmeshpy/__init__.py
distmeshpy/_internal.cpython-39-darwin.so
distmeshpy/_tetrahedron_utils.cpython-39-darwin.so
distmeshpy/_triangle_utils.cpython-39-darwin.so
distmeshpy/_typing.py
distmeshpy/internal.py
distmeshpy/tetrahedron_utils.py
distmeshpy/triangle_utils.py
distmeshpy/src/internal.cpp
distmeshpy/src/tetrahedron_utils.cpp
distmeshpy/src/triangle_utils.cpp
distmeshpy-1.1.0.dist-info/licenses/LICENSE
distmeshpy-1.1.0.dist-info/METADATA
distmeshpy-1.1.0.dist-info/WHEEL
distmeshpy-1.1.0.dist-info/top_level.txt
distmeshpy-1.1.0.dist-info/RECORD
