Metadata-Version: 2.4
Name: distmeshpy
Version: 1.1.0
Summary: A Python implemenetation of the distmesh algorithm
Author-email: Songyuan Cui <cui20@illinois.edu>
License-Expression: GPL-3.0-or-later
Project-URL: repository, https://github.com/sy-cui/distmeshpy.git
Classifier: Development Status :: 4 - Beta
Classifier: Intended Audience :: Science/Research
Classifier: Programming Language :: Python :: 3
Classifier: Programming Language :: Python :: 3.9
Classifier: Programming Language :: Python :: 3.10
Classifier: Programming Language :: Python :: 3.11
Classifier: Programming Language :: Python :: 3.12
Classifier: Topic :: Scientific/Engineering
Requires-Python: >=3.9
License-File: LICENSE
Requires-Dist: scipy>=1.13.0
Requires-Dist: matplotlib>=3.8.0
Requires-Dist: PyMCubes>=0.1.0
Provides-Extra: dev
Requires-Dist: mypy; extra == "dev"
Requires-Dist: pre-commit; extra == "dev"
Provides-Extra: test
Requires-Dist: pytest; extra == "test"
Requires-Dist: tox; extra == "test"
Provides-Extra: linter
Requires-Dist: ruff; extra == "linter"
Dynamic: license-file
